datasette_import/__init__.py
datasette_import/static/papaparse-5-4-1.min.js
datasette_import/templates/import_create_table.html
datasette_import-0.1a6.dist-info/licenses/LICENSE
datasette_import-0.1a6.dist-info/METADATA
datasette_import-0.1a6.dist-info/WHEEL
datasette_import-0.1a6.dist-info/entry_points.txt
datasette_import-0.1a6.dist-info/top_level.txt
datasette_import-0.1a6.dist-info/RECORD
