Metadata-Version: 2.4
Name: datasette-import
Version: 0.1a6
Summary: Tools for importing data into Datasette
Author: Datasette
License: Apache-2.0
Project-URL: Homepage, https://github.com/datasette/datasette-import
Project-URL: Changelog, https://github.com/datasette/datasette-import/releases
Project-URL: Issues, https://github.com/datasette/datasette-import/issues
Project-URL: CI, https://github.com/datasette/datasette-import/actions
Classifier: Framework :: Datasette
Classifier: License :: OSI Approved :: Apache Software License
Requires-Python: >=3.8
License-File: LICENSE
Requires-Dist: datasette==1.0a19
Provides-Extra: test
Requires-Dist: pytest; extra == "test"
Requires-Dist: pytest-asyncio; extra == "test"
Dynamic: license-file
